facturapyme/__init__.py
facturapyme/sdk.py
facturapyme-1.0.0.dist-info/LICENSE
facturapyme-1.0.0.dist-info/METADATA
facturapyme-1.0.0.dist-info/WHEEL
facturapyme-1.0.0.dist-info/top_level.txt
facturapyme-1.0.0.dist-info/RECORD
