Metadata-Version: 2.1
Name: facturapyme
Version: 1.0.0
Summary: Python SDK para integrar API de facturapy.me
Home-page: https://github.com/blackxel/facturapyme-sdk-python
Author: Blackxel
Author-email: dev@blackxel.com
License: UNKNOWN
Platform: UNKNOWN
Classifier: Intended Audience :: Developers
Classifier: Programming Language :: Python :: 2
Classifier: Programming Language :: Python :: 3
Classifier: License :: Public Domain
Classifier: Operating System :: OS Independent
